setup.cfg
setup.py
docs/HISTORY.txt
docs/INSTALL.txt
docs/LICENSE.GPL
docs/LICENSE.txt
iscorpio/__init__.py
iscorpio.plonepm.egg-info/PKG-INFO
iscorpio.plonepm.egg-info/SOURCES.txt
iscorpio.plonepm.egg-info/dependency_links.txt
iscorpio.plonepm.egg-info/entry_points.txt
iscorpio.plonepm.egg-info/namespace_packages.txt
iscorpio.plonepm.egg-info/not-zip-safe
iscorpio.plonepm.egg-info/requires.txt
iscorpio.plonepm.egg-info/top_level.txt
iscorpio/plonepm/README.txt
iscorpio/plonepm/TODO.txt
iscorpio/plonepm/__init__.py
iscorpio/plonepm/config.py
iscorpio/plonepm/configure.zcml
iscorpio/plonepm/permissions.py
iscorpio/plonepm/refresh.txt
iscorpio/plonepm/setuphanlders.py
iscorpio/plonepm/skins.zcml
iscorpio/plonepm/utils.py
iscorpio/plonepm/version.txt
iscorpio/plonepm/browser/__init__.py
iscorpio/plonepm/browser/configure.zcml
iscorpio/plonepm/browser/interfaces.py
iscorpio/plonepm/browser/iteration.py
iscorpio/plonepm/browser/iteration_view.pt
iscorpio/plonepm/browser/iterations_view.pt
iscorpio/plonepm/browser/metadata_view.pt
iscorpio/plonepm/browser/project.pt
iscorpio/plonepm/browser/project.py
iscorpio/plonepm/browser/stories_view.pt
iscorpio/plonepm/browser/story.py
iscorpio/plonepm/browser/story_view.pt
iscorpio/plonepm/browser/timesheet.py
iscorpio/plonepm/browser/timesheet_changelog.pt
iscorpio/plonepm/browser/timesheet_form.pt
iscorpio/plonepm/browser/useCase_view.pt
iscorpio/plonepm/browser/useCases_view.pt
iscorpio/plonepm/content/PPMArtifact.py
iscorpio/plonepm/content/PPMBuildJournal.py
iscorpio/plonepm/content/PPMFuncReq.py
iscorpio/plonepm/content/PPMFuncSpec.py
iscorpio/plonepm/content/PPMIteration.py
iscorpio/plonepm/content/PPMMetadata.py
iscorpio/plonepm/content/PPMProject.py
iscorpio/plonepm/content/PPMResponse.py
iscorpio/plonepm/content/PPMStory.py
iscorpio/plonepm/content/PPMSysReq.py
iscorpio/plonepm/content/PPMUseCase.py
iscorpio/plonepm/content/__init__.py
iscorpio/plonepm/content/base.py
iscorpio/plonepm/content/buildjournal.py
iscorpio/plonepm/content/issue.py
iscorpio/plonepm/content/memo.py
iscorpio/plonepm/content/project.py
iscorpio/plonepm/content/proposal.py
iscorpio/plonepm/content/release.py
iscorpio/plonepm/content/story.py
iscorpio/plonepm/content/task.py
iscorpio/plonepm/content/xpointdoc.py
iscorpio/plonepm/interfaces/__init__.py
