Metadata-Version: 1.0
Name: iscorpio.plonepm
Version: 2.0beta2-r382
Summary: A Plone way to manage project
Home-page: http://plonexp.leocorn.com/plonepm
Author: Sean Chen
Author-email: sean.chen@leocorn.com
License: GPL
Keywords: Python Plone Zope Project Management
Platform: UNKNOWN
Classifier: Development Status :: 4 - Beta
Classifier: Environment :: Web Environment
Classifier: Framework :: Plone
Classifier: Intended Audience :: Information Technology
Classifier: License :: OSI Approved :: GNU General Public License (GPL)
Classifier: Programming Language :: Python
Classifier: Programming Language :: Zope
Classifier: Topic :: Software Development :: Documentation
Classifier: Topic :: Software Development :: Libraries :: Python Modules
